data_asset_manager/__init__.py
data_asset_manager/main.py
data_asset_manager-2.4.1.dist-info/LICENSE
data_asset_manager-2.4.1.dist-info/METADATA
data_asset_manager-2.4.1.dist-info/WHEEL
data_asset_manager-2.4.1.dist-info/top_level.txt
data_asset_manager-2.4.1.dist-info/RECORD
