Metadata-Version: 2.2
Name: data-asset-manager
Version: 2.4.1
Summary: A Pandas wrapper library that simplifies day-to-day data management tasks
Author-email: Jon Hart <hartjc@gmail.com>
Project-URL: Source Code, https://github.com/jc-hart/stop-watch
Project-URL: Bug Tracker, https://github.com/jc-hart/stop-watch/issues
Classifier: Programming Language :: Python :: 3
Classifier: Operating System :: Microsoft :: Windows
Classifier: License :: OSI Approved :: GNU General Public License v3 (GPLv3)
Requires-Python: >=3.10
License-File: LICENSE
Requires-Dist: log-manager<2.0,>=1.0
